{"SWITCH Market price determination": [1.0, 2.0], "SWITCH TGC obligation curve": [1.0, 2.0], "SWITCH carbon cap": [1.0, 2.0], "SWITCH carbon price determination": [1.0, 2.0], "SWITCH economic growth": [1.0, 2.0], "SWITCH electrification rate": [1.0, 2.0], "SWITCH interconnection capacity expansion": [1.0, 2.0], "SWITCH lookup curve TGC": [1.0, 2.0], "SWITCH low reserve margin price markup": [1.0, 2.0], "SWITCH physical limits": [1.0, 2.0], "SWITCH storage for intermittent supply": [1.0, 2.0], "SWTICH preference carbon curve": [1.0, 2.0], "demand fuel price elasticity factor": [0.0, 0.5], "economic lifetime biomass": [30.0, 50.0], "economic lifetime coal": [30.0, 50.0], "economic lifetime gas": [25.0, 40.0], "economic lifetime hydro": [50.0, 70.0], "economic lifetime igcc": [30.0, 50.0], "economic lifetime ngcc": [25.0, 40.0], "economic lifetime nuclear": [50.0, 70.0], "economic lifetime pv": [20.0, 30.0], "economic lifetime wind": [20.0, 30.0], "investment proportionality constant": [0.5, 4.0], "investors desired excess capacity investment": [0.2, 2.0], "maximum battery storage uncertainty constant": [0.2, 3.0], "maximum no storage penetration rate pv": [0.1, 0.4], "maximum no storage penetration rate wind": [0.2, 0.6], "price demand elasticity factor": [-0.07, -0.001], "price volatility global resource markets": [0.1, 0.2], "progress ratio biomass": [0.85, 1.0], "progress ratio coal": [0.9, 1.05], "progress ratio gas": [0.85, 1.0], "progress ratio hydro": [0.9, 1.05], "progress ratio igcc": [0.9, 1.05], "progress ratio ngcc": [0.85, 1.0], "progress ratio nuclear": [0.9, 1.05], "progress ratio pv": [0.75, 0.9], "progress ratio wind": [0.85, 1.0], "starting construction time": [0.1, 3.0], "time of nuclear power plant ban": [2013.0, 2100.0], "uncertainty initial gross fuel costs": [0.5, 1.5], "weight factor carbon abatement": [1.0, 10.0], "weight factor marginal investment costs": [1.0, 10.0], "weight factor technological familiarity": [1.0, 10.0], "weight factor technological growth potential": [1.0, 10.0], "year": [0.9, 1.1]}